dynamo_db_resource/__init__.py
dynamo_db_resource/__main__.py
dynamo_db_resource/_number_types_in_objects.py
dynamo_db_resource/_schema.py
dynamo_db_resource/conditions.py
dynamo_db_resource/dynamo_db_table.py
dynamo_db_resource/dynamodb_schema.json
dynamo_db_resource/exceptions.py
dynamo_db_resource/resource.py
dynamo_db_resource/resource_config.py
dynamo_db_resource/table_existence.py
tests/__init__.py
tests/test_cast_infrastructure.py
tests/test_database_resource.py
tests/test_dynamodb.py
tests/test_main.py
tests/test_number_types_in_objects.py
tests/test_resource_config.py
tests/test_schema.py
dynamo_db_resource-0.7.1.dist-info/LICENSE
dynamo_db_resource-0.7.1.dist-info/METADATA
dynamo_db_resource-0.7.1.dist-info/WHEEL
dynamo_db_resource-0.7.1.dist-info/top_level.txt
dynamo_db_resource-0.7.1.dist-info/RECORD
