Metadata-Version: 2.1
Name: dynamo-db-resource
Version: 0.7.1
Summary: abstraction of AWS Dynamo DB
Home-page: https://github.com/janluak/dynamo_db_resource
Author: Jan Lukas Braje
Author-email: aws_dynamo_db@getkahawa.com
License: UNKNOWN
Platform: UNKNOWN
Classifier: Development Status :: 3 - Alpha
Classifier: Intended Audience :: Information Technology
Classifier: License :: OSI Approved :: Apache Software License
Classifier: Operating System :: OS Independent
Classifier: Programming Language :: Python :: 3.8
Requires-Python: >=3.8
Requires-Dist: boto3
Requires-Dist: botocore
Requires-Dist: jsonschema
Requires-Dist: aws-schema >=0.2.2
